Lab09/p3/DataMemory.v
`timescale 1ns / 1ps

`define SIZE 1024

module DataMemory(ReadData , Address , WriteData , MemoryRead , MemoryWrite , Clock);
    input [63:0]      WriteData;
    input [63:0]      Address;
    input             Clock, MemoryRead, MemoryWrite;
    output reg [63:0] ReadData;

    reg [7:0]         memBank [`SIZE-1:0];


    // This task is used to write arbitrary data to the Data Memory by
    // the intialization block.
    task initset;
      input [63:0] addr;
      input [63:0] data;
      begin
     memBank[addr] =  data[63:56] ; // Big-endian for the win...
     memBank[addr+1] =  data[55:48];
     memBank[addr+2] =  data[47:40];
     memBank[addr+3] =  data[39:32];
     memBank[addr+4] =  data[31:24];
     memBank[addr+5] =  data[23:16];
     memBank[addr+6] =  data[15:8];
     memBank[addr+7] =  data[7:0];
      end
    endtask


    initial
    begin
        // preseting some data in the data memory used by test #1

        // Address 0x0 gets 0x1
        initset( 64'h0,  64'h1);  //Counter variable
        initset( 64'h8,  64'ha);  //Part of mask
        initset( 64'h10, 64'h5);  //Other part of mask
        initset( 64'h18, 64'h0ffbea7deadbeeff); //big constant
        initset( 64'h20, 64'h0); //clearing space
        initset( 64'h30, 64'h123456789abc0000);

        // Add any data you need for your tests here.

    end

    // This always block reads the data memory and places a double word
    // on the ReadData bus.
    always @(posedge Clock)
    begin
        if(MemoryRead)
        begin
            ReadData[63:56] <= #20 memBank[Address];
            ReadData[55:48] <= #20 memBank[Address+1];
            ReadData[47:40] <= #20 memBank[Address+2];
            ReadData[39:32] <= #20 memBank[Address+3];
            ReadData[31:24] <= #20 memBank[Address+4];
            ReadData[23:16] <= #20 memBank[Address+5];
            ReadData[15:8] <= #20 memBank[Address+6];
            ReadData[7:0] <= #20 memBank[Address+7];
        end
    end

    // This always block takes data from the WriteData bus and writes
    // it into the DataMemory.
    always @(posedge Clock)
    begin
        if(MemoryWrite)
        begin
            memBank[Address] <= #20 WriteData[63:56] ;
            memBank[Address+1] <= #20 WriteData[55:48];
            memBank[Address+2] <= #20 WriteData[47:40];
            memBank[Address+3] <= #20 WriteData[39:32];
            memBank[Address+4] <= #20 WriteData[31:24];
            memBank[Address+5] <= #20 WriteData[23:16];
            memBank[Address+6] <= #20 WriteData[15:8];
            memBank[Address+7] <= #20 WriteData[7:0];
            // Could be useful for debugging:
            // $display("Writing Address:%h Data:%h",Address, WriteData);
        end
    end
endmodule

Lab07/ALU-2.v
`timescale 1ns / 1ps

`define AND   4'b0000
`define OR    4'b0001
`define ADD   4'b0010
`define LSL   4'b0011
`define LSR   4'b0100
`define SUB   4'b0110
`define PassB 4'b0111

module ALU(BusW, BusA, BusB, ALUCtrl, Zero);
    
    parameter n = 64;

    output  [n-1:0] BusW;
    input   [n-1:0] BusA, BusB;
    input   [3:0] ALUCtrl;
    output  Zero;
    
    reg     [n-1:0] BusW;
    
    always @(ALUCtrl or BusA or BusB) begin
        case(ALUCtrl)
            `AND: begin
                BusW <= #20 BusA & BusB;
            end
            `OR: begin
                BusW <= #20 BusA | BusB;
            end
            `LSL: begin
                BusW <= #20 BusA << BusB;
            end
            `LSR: begin
                BusW <= #20 BusA >> BusB;
            end
            `ADD: begin
                BusW <= #20 BusA + BusB;
            end
            `SUB: begin
                BusW <= #20 BusA - BusB;
            end
            `PassB: begin
                BusW <= #20 BusB;
            end
        endcase
    end
    
    assign #1 Zero = (BusW == 0) ? 1:0;
endmodule

Lab09/SignExtender.v
`timescale 1ns / 1ps

module SignExtender(BusImm, Imm26, Ctrl); 
  output reg [63:0] BusImm; 
  input [25:0] Imm26; 
  input [1:0]Ctrl; 

  wire extBit; 
  assign #1 extBit = (Ctrl ? 1'b0 : Imm26[25]); 
  
  always @(*) begin
    if(Ctrl == 2'b00)                             // I type
        BusImm = {{52{1'b0}},Imm26[21:10]};
    else if(Ctrl == 2'b01)                        // D type
        BusImm = {{55{Imm26[20]}},Imm26[20:12]};
    else if(Ctrl == 2'b10)                        // B
        BusImm = {{38{Imm26[25]}},Imm26};
    else                                          // CB
        BusImm = {{45{Imm26[23]}},Imm26[23:5]};
  end

endmodule

Lab09/RegisterFile.v
`timescale 1ns/ 1ps

module RegisterFile(BusA, BusB, BusW, RA, RB, RW, RegWr, Clk);
    output [63:0] BusA;
    output [63:0] BusB;
    input [63:0] BusW;
    input [4:0] RA, RB, RW;
    input RegWr;
    input Clk;
    reg [63:0] registers [31:0];

    // start by setting 31 to 0
    initial begin
        registers[31] = 0;
    end

    //every two ticks, Buses A and B are updated
    assign #2 BusA = registers[RA];
    assign #2 BusB = registers[RB];
     
    //on the clocks negative edge, update the register at Rw
    always @ (negedge Clk) begin
        if(RegWr) 
            if(RW != 31)  // 31 must always be 0
               registers[RW] <= #3 BusW; 
    end
endmodule

Lab09/SingleCycleControl.v
`define OPCODE_ANDREG 11'b?0001010???
`define OPCODE_ORRREG 11'b?0101010???
`define OPCODE_ADDREG 11'b?0?01011???
`define OPCODE_SUBREG 11'b?1?01011???

`define OPCODE_ADDIMM 11'b?0?10001???
`define OPCODE_SUBIMM 11'b?1?10001???

`define OPCODE_MOVZ   11'b110100101??

`define OPCODE_B      11'b?00101?????
`define OPCODE_CBZ    11'b?011010????

`define OPCODE_LDUR   11'b??111000010
`define OPCODE_STUR   11'b??111000000

module control(
    output reg reg2loc,
    output reg alusrc,
    output reg mem2reg,
    output reg regwrite,
    output reg memread,
    output reg memwrite,
    output reg branch,
    output reg uncond_branch,
    output reg [3:0] aluop,
    output reg [1:0] signop,
    input [10:0] opcode
);

always @(*)
begin
    casez (opcode)

        `OPCODE_ANDREG: begin
           	reg2loc       <= 1'b0;
            uncond_branch <= 1'b0;
            branch        <= 1'b0;
            memread       <= 1'b0;
            mem2reg       <= 1'b0;
            memwrite      <= 1'b0;
            alusrc        <= 1'b0;
            regwrite      <= 1'b1;
            aluop         <= 4'b0010;
            signop        <= 2'bxx;
        end

        `OPCODE_ORRREG: begin 
           	reg2loc       <= 1'b0;
            uncond_branch <= 1'b0;
            branch        <= 1'b0;
            memread       <= 1'b0;
            mem2reg       <= 1'b0;
            memwrite      <= 1'b0;
            alusrc        <= 1'b0;
            regwrite      <= 1'b1;
            aluop         <= 4'b0010;
            signop        <= 2'bxx;
        end

        `OPCODE_ADDREG: begin 
           	reg2loc       <= 1'b0;
            uncond_branch <= 1'b0;
            branch        <= 1'b0;
            memread       <= 1'b0;
            mem2reg       <= 1'b0;
            memwrite      <= 1'b0;
            alusrc        <= 1'b0;
            regwrite      <= 1'b1;
            aluop         <= 4'b0010;
            signop        <= 2'bxx;
        end

        `OPCODE_SUBREG: begin 
           	reg2loc       <= 1'b0;
            uncond_branch <= 1'b0;
            branch        <= 1'b0;
            memread       <= 1'b0;
            mem2reg       <= 1'b0;
            memwrite      <= 1'b0;
            alusrc        <= 1'b0;
            regwrite      <= 1'b1;
            aluop         <= 4'b0010;
            signop        <= 2'bxx;
        end

        `OPCODE_ADDIMM: begin 
           	reg2loc       <= 1'bx;
            uncond_branch <= 1'b0;
            branch        <= 1'b0;
            memread       <= 1'b0;
            mem2reg       <= 1'b0;
            memwrite      <= 1'b0;
            alusrc        <= 1'b1;
            regwrite      <= 1'b1;
            aluop         <= 4'b0010;
            signop        <= 2'b00;
        end

        `OPCODE_SUBIMM: begin 
           	reg2loc       <= 1'bx;
            uncond_branch <= 1'b0;
            branch        <= 1'b0;
            memread       <= 1'b0;
            mem2reg       <= 1'b0;
            memwrite      <= 1'b0;
            alusrc        <= 1'b1;
            regwrite      <= 1'b1;
            aluop         <= 4'b0010;
            signop        <= 2'b00;
        end

        // `OPCODE_MOVZ: begin 
        //    	reg2loc       <= 1'b0;
        //     uncond_branch <= 1'b0;
        //     branch        <= 1'b0;
        //     memread       <= 1'b0;
        //     mem2reg       <= 1'b0;
        //     memwrite      <= 1'b0;
        //     alusrc        <= 1'b0;
        //     regwrite      <= 1'b1;
        //     aluop         <= 4'b0010;
        //     signop        <= 2'bxx;
        // end

        `OPCODE_B: begin 
           	reg2loc       <= 1'bx;
            uncond_branch <= 1'b1;
            branch        <= 1'bx;
            memread       <= 1'b0;
            mem2reg       <= 1'bx;
            memwrite      <= 1'b0;
            alusrc        <= 1'bx;
            regwrite      <= 1'b0;
            aluop         <= 4'b00xx;
            signop        <= 2'b10;
        end

        `OPCODE_CBZ: begin 
           	reg2loc       <= 1'b1;
            uncond_branch <= 1'b0;
            branch        <= 1'b1;
            memread       <= 1'b0;
            mem2reg       <= 1'bx;
            memwrite      <= 1'b0;
            alusrc        <= 1'b0;
            regwrite      <= 1'b0;
            aluop         <= 4'b0001;
            signop        <= 2'b11;
        end

        `OPCODE_LDUR: begin 
           	reg2loc       <= 1'bx;
            uncond_branch <= 1'b0;
            branch        <= 1'b0;
            memread       <= 1'b1;
            mem2reg       <= 1'b1;
            memwrite      <= 1'b0;
            alusrc        <= 1'b1;
            regwrite      <= 1'b1;
            aluop         <= 4'b0010;
            signop        <= 2'b01;
        end

        `OPCODE_STUR: begin 
           	reg2loc       <= 1'b1;
            uncond_branch <= 1'b0;
            branch        <= 1'b0;
            memread       <= 1'b0;
            mem2reg       <= 1'bx;
            memwrite      <= 1'b1;
            alusrc        <= 1'b1;
            regwrite      <= 1'b0;
            aluop         <= 4'b0000;
            signop        <= 2'b01;
        end

        default: begin
            reg2loc       <= 1'bx;
            alusrc        <= 1'bx;
            mem2reg       <= 1'bx;
            regwrite      <= 1'b0;
            memread       <= 1'b0;
            memwrite      <= 1'b0;
            branch        <= 1'b0;
            uncond_branch <= 1'b0;
            aluop         <= 4'bxxxx;
            signop        <= 2'bxx;
        end
    endcase
end

endmodule

Lab09/p3/NextPCLogic.v
`timescale 1ns / 1ps

module NextPCLogic(NextPC, CurrentPC, SignExtImm64, Branch, ALUZero, Uncondbranch); 
    input [63:0] CurrentPC, SignExtImm64; 
    input Branch, ALUZero, Uncondbranch; 
    output reg [63:0] NextPC; 
    reg [63:0] realImm64;

    always @(*) begin
    
        //sign extended values have two meaningless 0's attatched
        //so we have to shift left by two to remove them and have a 
        //correct binary instruction
        realImm64 = SignExtImm64 << 2; 

        if(Uncondbranch) //update pc to jump to our branched address
            NextPC  <= #2 CurrentPC + realImm64; 
        else if(Branch) //same thing as unconditionalBranch but only if ALUZero is 1
            if(ALUZero == 1)
                NextPC <= #2 CurrentPC + realImm64; 
            else
                NextPC <= #2 CurrentPC + 4; 
        else //in the case of a non branching instruction
            NextPC <= #2 CurrentPC + 4; 
    end

endmodule

Lab09/InstructionMemory-1.v
`timescale 1ns / 1ps
/*
 * Module: InstructionMemory
 *
 * Implements read-only instruction memory
 * 
 */
module InstructionMemory(Data, Address);
   parameter T_rd = 20;
   parameter MemSize = 40;
   
   output [31:0] Data;
   input [63:0]  Address;
   reg [31:0] 	 Data;
   
   always @ (Address) begin
      #4;
      case(Address)

	/* Test Program 1:
	 * Program loads constants from the data memory. Uses these constants to test
	 * the following instructions: LDUR, ORR, AND, CBZ, ADD, SUB, STUR and B.
	 * 
	 * Assembly code for test:
	 * 
	 * 0: LDUR X9, [XZR, 0x0]    //Load 1 into x9
	 * 4: LDUR X10, [XZR, 0x8]   //Load a into x10
	 * 8: LDUR X11, [XZR, 0x10]  //Load 5 into x11
	 * C: LDUR X12, [XZR, 0x18]  //Load big constant into x12
	 * 10: LDUR X13, [XZR, 0x20]  //load a 0 into X13
	 * 
	 * 14: ORR X10, X10, X11  //Create mask of 0xf
	 * 18: AND X12, X12, X10  //Mask off low order bits of big constant
	 * 
	 * loop:
	 * 1C: CBZ X12, end  //while X12 is not 0
	 * 20: ADD X13, X13, X9  //Increment counter in X13
	 * 24: SUB X12, X12, X9  //Decrement remainder of big constant in X12
	 * 28: B loop  //Repeat till X12 is 0
	 * 2C: STUR X13, [XZR, 0x20]  //store back the counter value into the memory location 0x20
	 */

	//  0: LDUR X11, [XZR, 0x10]  //Load 5 into x11
	//  4: STUR X11, [XZR, 0x20]

	 63'h000: Data = 32'hF84083EA;
	 63'h008: Data = 32'hF80203EA;
	

	 /*63'h000: Data = 32'hF84003E9;
	 63'h004: Data = 32'hF84083EA;
	 63'h008: Data = 32'hF84103EB;
	 63'h00c: Data = 32'hF84183EC;
	 63'h010: Data = 32'hF84203ED;
	 63'h014: Data = 32'hAA0B014A;
	 63'h018: Data = 32'h8A0A018C;
	 63'h01c: Data = 32'hB400008C;
	 63'h020: Data = 32'h8B0901AD;
	 63'h024: Data = 32'hCB09018C;
	 63'h028: Data = 32'h17FFFFFD;
	 63'h02c: Data = 32'hF80203ED;
	 63'h030: Data = 32'hF84203ED;  //One last load to place stored value on memdbus for test checking. */

	/* Add code for your tests here */

			
	default: Data = 32'hXXXXXXXX;
      endcase
   end
endmodule

Lab09/SingleCycleProc.v
`include "ALU-2.v"
`include "DataMemory.v"
`include "InstructionMemory-1.v"
`include "NextPCLogic.v"
`include "RegisterFile.v"
`include "SignExtender.v"
`include "SingleCycleControl.v"

module singlecycle(
    input resetl,
    input [63:0] startpc,
    output reg [63:0] currentpc,
    output [63:0] dmemout,
    input CLK
);
    //WIRES

    // Next PC connections
    wire [63:0] nextpc;       // The next PC, to be updated on clock cycle

    // Instruction Memory connections
    wire [31:0] instruction;  // The current instruction

    // Parts of instruction
    wire [4:0] rd;            // The destination register
    wire [4:0] rm;            // Operand 1
    wire [4:0] rn;            // Operand 2
    wire [10:0] opcode;

    // Control wires
    wire reg2loc;
    wire alusrc;
    wire mem2reg;
    wire regwrite;
    wire memread;
    wire memwrite;
    wire branch;
    wire uncond_branch;
    wire [3:0] aluctrl;
    wire [1:0] signop;

    // Register file connections
    wire [63:0] regoutA, regoutB, busw;     // Outputs A and B

    // ALU connections
    wire [63:0] signExtImm64, aluBusB, aluout;
    wire zero;

    // Sign Extender connections
    wire [63:0] extimm;

    // PC update logic
    always @(negedge CLK)
    begin
        if (resetl)
            currentpc <= nextpc;
        else
            currentpc <= startpc;
    end

    // Parts of instruction
    assign rd = instruction[4:0];
    assign rm = instruction[9:5];
    assign rn = reg2loc ? instruction[4:0] : instruction[20:16];
    assign opcode = instruction[31:21];


    //MODULES 

    InstructionMemory imem(
        .Data(instruction),
        .Address(currentpc)
    );

    NextPCLogic nextPCLogic(
        .NextPC(nextpc), 
        .CurrentPC(currentpc), 
        .SignExtImm64(signExtImm64), 
        .Branch(branch), 
        .ALUZero(zero), 
        .Uncondbranch(uncond_branch)
    ); 

    control control(
        .reg2loc(reg2loc),
        .alusrc(alusrc),
        .mem2reg(mem2reg),
        .regwrite(regwrite),
        .memread(memread),
        .memwrite(memwrite),
        .branch(branch),
        .uncond_branch(uncond_branch),
        .aluop(aluctrl),
        .signop(signop),
        .opcode(opcode)
    );

    RegisterFile regfile(
        .BusA(regoutA), 
        .BusB(regoutB), 
        .BusW(busw), 
        .RA(rm), 
        .RB(rn), 
        .RW(rd), 
        .RegWr(regwrite), 
        .Clk(CLK)
    );

    SignExtender signextender(
        .BusImm(signExtImm64), 
        .Imm26(instruction[31:6]), 
        .Ctrl(signop)
    );

    assign aluBusB = alusrc ? signExtImm64 : regoutB;

    ALU ALU(
        .BusW(aluout), 
        .BusA(regoutA), 
        .BusB(aluBusB), //multiplexed with ternary logic for regoutA higher up in code
        .ALUCtrl(aluctrl), 
        .Zero(zero)
    );

    DataMemory dataMem(
        .ReadData(dmemout), 
        .Address(aluout), 
        .WriteData(regoutB), 
        .MemoryRead(memread), 
        .MemoryWrite(memwrite), 
        .Clock(CLK)
    );

    assign busw = mem2reg ? dmemout : aluout;


endmodule

Lab09/SingleCycleProcTest.v
`timescale 1ns / 1ps

//`include "SingleCycleProc.v"

`define STRLEN 32
`define HalfClockPeriod 60
`define ClockPeriod `HalfClockPeriod * 2

module SingleCycleProcTest_v;

    initial
    begin
        $dumpfile("singlecycle.vcd");
        $dumpvars;
    end

    task passTest;
        input [63:0] actualOut, expectedOut;
        input [`STRLEN*8:0] testType;
        inout [7:0] 	  passed;

        if(actualOut == expectedOut) begin $display ("%s passed", testType); passed = passed + 1; end
        else $display ("%s failed: 0x%x should be 0x%x", testType, actualOut, expectedOut);
    endtask

    task allPassed;
        input [7:0] passed;
        input [7:0] numTests;

        if(passed == numTests) $display ("All tests passed");
        else $display("Some tests failed: %d of %d passed", passed, numTests);
    endtask

    // Inputs
    reg        CLK;
    reg        Reset_L;
    reg [63:0] startPC;
    reg [7:0]  passed;
    reg [15:0] watchdog;

    // Outputs
    wire [63:0] dMemOut;
    wire [63:0] currentPC;

    // Instantiate the Unit Under Test (UUT)
    singlecycle uut (
        .CLK(CLK),
        .resetl(Reset_L),
        .startpc(startPC),
        .currentpc(currentPC),
        .dmemout(dMemOut)
    );

    initial begin
        // Initialize Inputs
        Reset_L = 1;
        startPC = 0;
        passed = 0;

        // Initialize Watchdog timer
        watchdog = 0;

        // Wait for global reset
        #(1 * `ClockPeriod);

        // Program 1
        #1
        Reset_L = 0; startPC = 0;
        #(1 * `ClockPeriod);
        Reset_L = 1;

        // ***********************************************************
        // This while loop will continue cycling the processor until the
        // PC reaches the final instruction in the first test.  If the
        // program forms an infinite loop, never reaching the end, the
        // watchdog timer will kick in and kill simulation after 64K
        // cycles.
        // ***********************************************************

        while (currentPC < 64'h34)
        begin
           #(1 * `ClockPeriod);
           $display("CurrentPC:%h",currentPC);
        end

        #(1 * `ClockPeriod);	// One more cycle to load the pass code from the DataMemory.
        passTest(dMemOut, 64'hf, "Results of Program 1", passed);

        // ***********************************************************
        // Add your new tests here
        // ***********************************************************

        // Done
        allPassed(passed, 1);   // Be sure to change the one to match
                                // the number of tests you add.
        $finish;
    end

    initial begin
        CLK = 0;
    end

    // The following is correct if clock starts at LOW level at StartTime //
    always begin
        #`HalfClockPeriod CLK = ~CLK;
        #`HalfClockPeriod CLK = ~CLK;
        watchdog = watchdog +1;
    end

    // Kill the simulation if the watchdog hits 64K cycles
    always @*
        if (watchdog == 16'hFF)
        begin
            $display("Watchdog Timer Expired.");
            $finish;
        end


endmodule

Lab09/singlecycle.vcd
$date
	Mon Nov 30 02:35:31 2020
$end
$version
	Icarus Verilog
$end
$timescale
	1ps
$end
$scope module SingleCycleProcTest_v $end
$var wire 64 ! dMemOut [63:0] $end
$var wire 64 " currentPC [63:0] $end
$var reg 1 # CLK $end
$var reg 1 $ Reset_L $end
$var reg 8 % passed [7:0] $end
$var reg 64 & startPC [63:0] $end
$var reg 16 ' watchdog [15:0] $end
$scope module uut $end
$var wire 1 # CLK $end
$var wire 1 $ resetl $end
$var wire 64 ( startpc [63:0] $end
$var wire 1 ) zero $end
$var wire 1 * uncond_branch $end
$var wire 2 + signop [1:0] $end
$var wire 64 , signExtImm64 [63:0] $end
$var wire 5 - rn [4:0] $end
$var wire 5 . rm [4:0] $end
$var wire 1 / regwrite $end
$var wire 64 0 regoutB [63:0] $end
$var wire 64 1 regoutA [63:0] $end
$var wire 1 2 reg2loc $end
$var wire 5 3 rd [4:0] $end
$var wire 11 4 opcode [10:0] $end
$var wire 64 5 nextpc [63:0] $end
$var wire 1 6 memwrite $end
$var wire 1 7 memread $end
$var wire 1 8 mem2reg $end
$var wire 32 9 instruction [31:0] $end
$var wire 64 : dmemout [63:0] $end
$var wire 64 ; busw [63:0] $end
$var wire 1 < branch $end
$var wire 1 = alusrc $end
$var wire 64 > aluout [63:0] $end
$var wire 4 ? aluctrl [3:0] $end
$var wire 64 @ aluBusB [63:0] $end
$var reg 64 A currentpc [63:0] $end
$scope module ALU $end
$var wire 64 B BusB [63:0] $end
$var wire 1 ) Zero $end
$var wire 64 C BusA [63:0] $end
$var wire 4 D ALUCtrl [3:0] $end
$var reg 64 E BusW [63:0] $end
$upscope $end
$scope module control $end
$var wire 11 F opcode [10:0] $end
$var reg 4 G aluop [3:0] $end
$var reg 1 = alusrc $end
$var reg 1 < branch $end
$var reg 1 8 mem2reg $end
$var reg 1 7 memread $end
$var reg 1 6 memwrite $end
$var reg 1 2 reg2loc $end
$var reg 1 / regwrite $end
$var reg 2 H signop [1:0] $end
$var reg 1 * uncond_branch $end
$upscope $end
$scope module dataMem $end
$var wire 64 I Address [63:0] $end
$var wire 1 # Clock $end
$var wire 1 7 MemoryRead $end
$var wire 1 6 MemoryWrite $end
$var wire 64 J WriteData [63:0] $end
$var reg 64 K ReadData [63:0] $end
$scope task initset $end
$var reg 64 L addr [63:0] $end
$var reg 64 M data [63:0] $end
$upscope $end
$upscope $end
$scope module imem $end
$var wire 64 N Address [63:0] $end
$var reg 32 O Data [31:0] $end
$upscope $end
$scope module nextPCLogic $end
$var wire 1 ) ALUZero $end
$var wire 1 < Branch $end
$var wire 64 P CurrentPC [63:0] $end
$var wire 1 * Uncondbranch $end
$var wire 64 Q SignExtImm64 [63:0] $end
$var reg 64 R NextPC [63:0] $end
$var reg 64 S realImm64 [63:0] $end
$upscope $end
$scope module regfile $end
$var wire 64 T BusA [63:0] $end
$var wire 64 U BusB [63:0] $end
$var wire 64 V BusW [63:0] $end
$var wire 1 # Clk $end
$var wire 5 W RA [4:0] $end
$var wire 5 X RB [4:0] $end
$var wire 5 Y RW [4:0] $end
$var wire 1 / RegWr $end
$upscope $end
$scope module signextender $end
$var wire 2 Z Ctrl [1:0] $end
$var wire 26 [ Imm26 [25:0] $end
$var wire 1 \ extBit $end
$var reg 64 ] BusImm [63:0] $end
$upscope $end
$upscope $end
$scope task allPassed $end
$var reg 8 ^ numTests [7:0] $end
$var reg 8 _ passed [7:0] $end
$upscope $end
$scope task passTest $end
$var reg 64 ` actualOut [63:0] $end
$var reg 64 a expectedOut [63:0] $end
$var reg 8 b passed [7:0] $end
$var reg 257 c testType [256:0] $end
$upscope $end
$upscope $end
$enddefinitions $end
#0
$dumpvars
bx c
bx b
bx a
bx `
bx _
bx ^
bx ]
x\
bx [
bx Z
bx Y
bx X
bx W
bx V
bx U
bx T
bx S
bx R
bx Q
bx P
bx O
bx N
b0 M
b100000 L
bx K
bx J
bx I
bx H
bx G
bx F
bx E
bx D
bx C
bx B
bx A
bx @
bx ?
bx >
x=
x<
bx ;
bx :
bx 9
x8
x7
x6
bx 5
bx 4
bx 3
x2
bx 1
bx 0
x/
bx .
bx -
bx ,
bx +
x*
x)
b0 (
b0 '
b0 &
b0 %
1$
0#
bx "
bx !
$end
#60000
1#
#120000
b1 '
0#
#121000
0$
#180000
1#
#240000
bx00 S
b0 "
b0 A
b0 N
b0 P
b10 '
0#
#241000
1$
#242000
b100 5
b100 R
#244000
b10000 @
b10000 B
b1 +
b1 H
b1 Z
b10 ?
b10 D
b10 G
1/
1=
06
18
17
0<
0*
b1000000 S
b10000 ,
b10000 Q
b10000 ]
b0x0x0 -
b0x0x0 X
b11111000010000001000001111 [
b11111000010 4
b11111000010 F
b11111 .
b11111 W
b1010 3
b1010 Y
b11111000010000001000001111101010 9
b11111000010000001000001111101010 O
#245000
0\
#246000
b0 1
b0 C
b0 T
#266000
b10000 >
b10000 E
b10000 I
#267000
0)
#300000
1#
#320000
b101 ;
b101 V
b101 !
b101 :
b101 K
#360000
b100 "
b100 A
b100 N
b100 P
b11 '
0#
#362000
b1000 5
b1000 R
#364000
b0x0x0x ;
b0x0x0x V
bx +
bx H
bx Z
bx ?
bx D
bx G
07
0/
x8
x=
bx @
bx B
bx00 S
bx ,
bx Q
bx ]
bx -
bx X
bx [
bx 4
bx F
bx .
bx W
bx 3
bx Y
bx 9
bx O
#365000
x\
#366000
bx 1
bx C
bx T
#384000
bx ;
bx V
bx >
bx E
bx I
#385000
x)
#420000
1#
#480000
b1000 "
b1000 A
b1000 N
b1000 P
b100 '
0#
#482000
b1100 5
b1100 R
#484000
b0 @
b0 B
b1 +
b1 H
b1 Z
b0 ?
b0 D
b0 G
1=
16
12
b0 S
b0 ,
b0 Q
b0 ]
b1010 -
b1010 X
b11111000000000100000001111 [
b11111000000 4
b11111000000 F
b11111 .
b11111 W
b1010 3
b1010 Y
b11111000000000100000001111101010 9
b11111000000000100000001111101010 O
#485000
0\
#486000
b101 0
b101 J
b101 U
b0 1
b0 C
b0 T
#504000
b0x0x ;
b0x0x V
b0 >
b0 E
b0 I
#505000
1)
#540000
1#
#600000
b1100 "
b1100 A
b1100 N
b1100 P
b101 '
0#
#602000
b10000 5
b10000 R
#604000
bx +
bx H
bx Z
bx ?
bx D
bx G
06
x=
x2
bx @
bx B
bx00 S
bx ,
bx Q
bx ]
bx -
bx X
bx [
bx 4
bx F
bx .
bx W
bx 3
bx Y
bx 9
bx O
#605000
x\
#606000
bx 0
bx J
bx U
bx 1
bx C
bx T
#660000
1#
#720000
b10000 "
b10000 A
b10000 N
b10000 P
b110 '
0#
#722000
b10100 5
b10100 R
#780000
1#
#840000
b10100 "
b10100 A
b10100 N
b10100 P
b111 '
0#
#842000
b11000 5
b11000 R
#900000
1#
#960000
b11000 "
b11000 A
b11000 N
b11000 P
b1000 '
0#
#962000
b11100 5
b11100 R
#1020000
1#
#1080000
b11100 "
b11100 A
b11100 N
b11100 P
b1001 '
0#
#1082000
b100000 5
b100000 R
#1140000
1#
#1200000
b100000 "
b100000 A
b100000 N
b100000 P
b1010 '
0#
#1202000
b100100 5
b100100 R
#1260000
1#
#1320000
b100100 "
b100100 A
b100100 N
b100100 P
b1011 '
0#
#1322000
b101000 5
b101000 R
#1380000
1#
#1440000
b101000 "
b101000 A
b101000 N
b101000 P
b1100 '
0#
#1442000
b101100 5
b101100 R
#1500000
1#
#1560000
b101100 "
b101100 A
b101100 N
b101100 P
b1101 '
0#
#1562000
b110000 5
b110000 R
#1620000
1#
#1680000
b110000 "
b110000 A
b110000 N
b110000 P
b1110 '
0#
#1682000
b110100 5
b110100 R
#1740000
1#
#1800000
b110100 "
b110100 A
b110100 N
b110100 P
b1111 '
0#
#1802000
b111000 5
b111000 R
#1860000
1#
#1920000
b111000 "
b111000 A
b111000 N
b111000 P
b10000 '
0#
#1921000
b1 ^
b0 _
b0 b
b101001001100101011100110111010101101100011101000111001100100000011011110110011000100000010100000111001001101111011001110111001001100001011011010010000000110001 c
b1111 a
b101 `
