Lab08/NextPCLogic.v
`timescale 1ns / 1ps

module NextPCLogic(NextPC, CurrentPC, SignExtImm64, Branch, ALUZero, Uncondbranch); 
    input [63:0] CurrentPC, SignExtImm64; 
    input Branch, ALUZero, Uncondbranch; 
    output reg [63:0] NextPC; 
    reg [63:0] realImm64;

    always @(*) begin
    
        //sign extended values have two meaningless 0's attatched
        //so we have to shift left by two to remove them and have a 
        //correct binary instruction
        realImm64 = SignExtImm64 << 2; 

        if(Uncondbranch) //update pc to jump to our branched address
            NextPC  <= #1 CurrentPC + realImm64; 
        else if(Branch) //same thing as unconditionalBranch but only if ALUZero is 1
            if(ALUZero == 1)
                NextPC <= #2 CurrentPC + realImm64; 
            else
                NextPC <= #2 CurrentPC + 4; 
        else //in the case of a non branching instruction
            NextPC <= #2 CurrentPC + 4; 
    end

endmodule

Lab08/NextPCLogicTest.v
`timescale 1ns / 1ps

`define STRLEN 32
module NextPCLogicTest;

	initial //This initial block used to dump all wire/reg values to dump file
     begin
       $dumpfile("NextPCLogicTest.vcd");
       $dumpvars(0,NextPCLogicTest);
     end

	task passTest;
		input [63:0] actualOut, expectedOut;
		input [`STRLEN*8:0] testType;
		inout [7:0] passed;
	
		if(actualOut == expectedOut) begin $display ("%s passed", testType); passed = passed + 1; end
		else $display ("%s failed: %d should be %d", testType, actualOut, expectedOut);
	endtask
	
	task allPassed;
		input [7:0] passed;
		input [7:0] numTests;
		
		if(passed == numTests) $display ("All tests passed");
		else $display("Some tests failed");
	endtask

	// Inputs
	reg [63:0] CurrentPC;
	reg [63:0] SignExtImm64;
	reg Branch;
	reg ALUZero;
	reg Uncondbranch;
	reg [7:0] passed;//not part of original verilog module

	// Outputs
	wire [63:0] NextPC;

	// Instantiate the Unit Under Test (UUT)
	NextPCLogic dut (
		.CurrentPC(CurrentPC),
		.SignExtImm64(SignExtImm64),
		.Branch(Branch),
		.ALUZero(ALUZero),
		.Uncondbranch(Uncondbranch),
		.NextPC(NextPC)
	);

	initial begin
		CurrentPC = 0;
		SignExtImm64 = 0;
		Branch = 0;
		ALUZero = 0;
		Uncondbranch = 0;
		passed = 0;
		
		#3;
		
		{CurrentPC, SignExtImm64, Branch, ALUZero, Uncondbranch} = {64'h10, 64'b0, 1'b0, 1'b0, 1'b0};
		#10 passTest(NextPC,64'h14,"PC+4",passed);
		$display (" CurrentPC: %d \n SignExtImm64: %b \n Branch: %d \n ALUZero: %d \n Uncondbranch: %d \n NextPC: %d \n", CurrentPC, SignExtImm64, Branch,ALUZero,Uncondbranch, NextPC);
		
		{CurrentPC, SignExtImm64, Branch, ALUZero, Uncondbranch} = {64'h10, 64'h2, 1'b1, 1'b1, 1'b0};
		#10 passTest(NextPC,64'h18,"Conditional with branching",passed);
		$display (" CurrentPC: %d \n SignExtImm64: %b \n Branch: %d \n ALUZero: %d \n Uncondbranch: %d \n NextPC: %d \n", CurrentPC, SignExtImm64, Branch,ALUZero,Uncondbranch, NextPC);
		
		{CurrentPC, SignExtImm64, Branch, ALUZero, Uncondbranch} = {64'h10, 64'h3, 1'b1, 1'b0, 1'b0};
		#10 passTest(NextPC,64'h14,"Conditional no branching",passed);
		$display (" CurrentPC: %d \n SignExtImm64: %b \n Branch: %d \n ALUZero: %d \n Uncondbranch: %d \n NextPC: %d \n", CurrentPC, SignExtImm64, Branch,ALUZero,Uncondbranch, NextPC);
		
		{CurrentPC, SignExtImm64, Branch, ALUZero, Uncondbranch} = {64'h10, 64'h4, 1'b0, 1'b0, 1'b1};
		#10 passTest(NextPC,64'h20,"Unconditional branching",passed);
		$display (" CurrentPC: %d \n SignExtImm64: %b \n Branch: %d \n ALUZero: %d \n Uncondbranch: %d \n NextPC: %d \n", CurrentPC, SignExtImm64, Branch,ALUZero,Uncondbranch, NextPC);

		allPassed(passed, 4);
	end
      
endmodule

Lab08/NextPCLogicTest.vcd
$date
	Mon Nov  9 14:27:13 2020
$end
$version
	Icarus Verilog
$end
$timescale
	1ps
$end
$scope module NextPCLogicTest $end
$var wire 64 ! NextPC [63:0] $end
$var reg 1 " ALUZero $end
$var reg 1 # Branch $end
$var reg 64 $ CurrentPC [63:0] $end
$var reg 64 % SignExtImm64 [63:0] $end
$var reg 1 & Uncondbranch $end
$var reg 8 ' passed [7:0] $end
$scope module dut $end
$var wire 1 " ALUZero $end
$var wire 1 # Branch $end
$var wire 64 ( CurrentPC [63:0] $end
$var wire 64 ) SignExtImm64 [63:0] $end
$var wire 1 & Uncondbranch $end
$var reg 64 * NextPC [63:0] $end
$var reg 64 + realImm64 [63:0] $end
$upscope $end
$scope task allPassed $end
$var reg 8 , numTests [7:0] $end
$var reg 8 - passed [7:0] $end
$upscope $end
$scope task passTest $end
$var reg 64 . actualOut [63:0] $end
$var reg 64 / expectedOut [63:0] $end
$var reg 8 0 passed [7:0] $end
$var reg 257 1 testType [256:0] $end
$upscope $end
$upscope $end
$enddefinitions $end
#0
$dumpvars
bx 1
bx 0
bx /
bx .
bx -
bx ,
b0 +
bx *
b0 )
b0 (
b0 '
0&
b0 %
b0 $
0#
0"
bx !
$end
#2000
b100 !
b100 *
#3000
b10000 $
b10000 (
#5000
b10100 !
b10100 *
#13000
b1000 +
b10 %
b10 )
1#
1"
b1 '
b1 0
b1010000010000110010101100110100 1
b10100 /
b10100 .
#15000
b11000 !
b11000 *
#23000
b1100 +
b11 %
b11 )
0"
b10 '
b10 0
b100001101101111011011100110010001101001011101000110100101101111011011100110000101101100001000000111011101101001011101000110100000100000011000100111001001100001011011100110001101101000011010010110111001100111 1
b11000 /
b11000 .
#25000
b10100 !
b10100 *
#33000
b10000 +
b100 %
b100 )
0#
1&
b11 '
b11 0
b10000110110111101101110011001000110100101110100011010010110111101101110011000010110110000100000011011100110111100100000011000100111001001100001011011100110001101101000011010010110111001100111 1
b10100 /
b10100 .
#34000
b100000 !
b100000 *
#43000
b100 ,
b100 -
b100 '
b100 0
b101010101101110011000110110111101101110011001000110100101110100011010010110111101101110011000010110110000100000011000100111001001100001011011100110001101101000011010010110111001100111 1
b100000 /
b100000 .
