Lab09/RegisterFile.v
`timescale 1ns/ 1ps

module RegisterFile(BusA, BusB, BusW, RA, RB, RW, RegWr, Clk);
    output [63:0] BusA;
    output [63:0] BusB;
    input [63:0] BusW;
    input [4:0] RA, RB, RW;
    input RegWr;
    input Clk;
    reg [63:0] registers [31:0];

    // start by setting 31 to 0
    initial begin
        registers[31] = 0;
    end

    //every two ticks, Buses A and B are updated
    assign #2 BusA = registers[RA];
    assign #2 BusB = registers[RB];
     
    //on the clocks negative edge, update the register at Rw
    always @ (negedge Clk) begin
        if(RegWr) 
            if(RW != 31)  // 31 must always be 0
               registers[RW] <= #3 BusW; 
    end
endmodule

Lab08/RegisterFileTest-2.v
`timescale 1ns / 1ps

`define STRLEN 32
module RegisterFileTest2_v;

		initial //This initial block used to dump all wire/reg values to dump file
     begin
       $dumpfile("RegisterFileTest2_v.vcd");
       $dumpvars(0,RegisterFileTest2_v);
     end

	task passTest;
		input [63:0] actualOut, expectedOut;
		input [`STRLEN*8:0] testType;
		inout [7:0] passed;
	
		if(actualOut == expectedOut) begin $display ("%s passed", testType); passed = passed + 1; end
		else $display ("%s failed: %d should be %d", testType, actualOut, expectedOut);
	endtask
	
	task allPassed;
		input [7:0] passed;
		input [7:0] numTests;
		
		if(passed == numTests) $display ("All tests passed");
		else $display("Some tests failed");
	endtask

	// Inputs
	reg [63:0] BusW;
	reg [4:0] RA;
	reg [4:0] RB;
	reg [4:0] RW;
	reg RegWr;
	reg Clk;
	reg [7:0] passed;

	// Outputs
	wire [63:0] BusA;
	wire [63:0] BusB;

	// Instantiate the Unit Under Test (UUT)
	RegisterFile dut (
		.BusA(BusA), 
		.BusB(BusB), 
		.BusW(BusW), 
		.RA(RA), 
		.RB(RB), 
		.RW(RW), 
		.RegWr(RegWr), 
		.Clk(Clk)
	);

	initial begin
		// Initialize Inputs
		BusW = 0;
		RA = 0;
		RB = 0;
		RW = 0;
		RegWr = 0;
		Clk = 1;
		passed = 0;
		
		#10;

		// Add stimulus here
		{RA, RB, RW, BusW, RegWr} = {5'd31, 5'd31, 5'd31, 64'h0, 1'b0};
		#10
		passTest(BusA, 64'd0, "Initial $0 Check 1", passed);
		passTest(BusB, 64'd0, "Initial $0 Check 2", passed);
		#10; Clk = 0; #10; Clk = 1;
		
		{RA, RB, RW, BusW, RegWr} = {5'd31, 5'd31, 5'd31, 64'h12345678, 1'b1};
		passTest(BusA, 64'd0, "Initial $0 Check 3", passed);
		passTest(BusB, 64'd0, "Initial $0 Check 4", passed);
		#10; Clk = 0; #10; Clk = 1;
		passTest(BusA, 64'd0, "$0 Stays 0 Check 1", passed);
		passTest(BusB, 64'd0, "$0 Stays 0 Check 2", passed);
		
		{RA, RB, RW, BusW, RegWr} = {5'd0, 5'd0, 5'd0, 64'h0, 1'b1};#10; Clk = 0; #10; Clk = 1;
		{RA, RB, RW, BusW, RegWr} = {5'd0, 5'd0, 5'd1, 64'h1, 1'b1};#10; Clk = 0; #10; Clk = 1;
		{RA, RB, RW, BusW, RegWr} = {5'd0, 5'd0, 5'd2, 64'h2, 1'b1};#10; Clk = 0; #10; Clk = 1;
		{RA, RB, RW, BusW, RegWr} = {5'd0, 5'd0, 5'd3, 64'h3, 1'b1};#10; Clk = 0; #10; Clk = 1;
		{RA, RB, RW, BusW, RegWr} = {5'd0, 5'd0, 5'd4, 64'h4, 1'b1};#10; Clk = 0; #10; Clk = 1;
		{RA, RB, RW, BusW, RegWr} = {5'd0, 5'd0, 5'd5, 64'h5, 1'b1};#10; Clk = 0; #10; Clk = 1;
		{RA, RB, RW, BusW, RegWr} = {5'd0, 5'd0, 5'd6, 64'h6, 1'b1};#10; Clk = 0; #10; Clk = 1;
		{RA, RB, RW, BusW, RegWr} = {5'd0, 5'd0, 5'd7, 64'h7, 1'b1};#10; Clk = 0; #10; Clk = 1;
		{RA, RB, RW, BusW, RegWr} = {5'd0, 5'd0, 5'd8, 64'h8, 1'b1};#10; Clk = 0; #10; Clk = 1;
		{RA, RB, RW, BusW, RegWr} = {5'd0, 5'd0, 5'd9, 64'h9, 1'b1};#10; Clk = 0; #10; Clk = 1;
		{RA, RB, RW, BusW, RegWr} = {5'd0, 5'd0, 5'd10, 64'd10, 1'b1};#10; Clk = 0; #10; Clk = 1;
		{RA, RB, RW, BusW, RegWr} = {5'd0, 5'd0, 5'd11, 64'd11, 1'b1};#10; Clk = 0; #10; Clk = 1;
		{RA, RB, RW, BusW, RegWr} = {5'd0, 5'd0, 5'd12, 64'd12, 1'b1};#10; Clk = 0; #10; Clk = 1;
		{RA, RB, RW, BusW, RegWr} = {5'd0, 5'd0, 5'd13, 64'd13, 1'b1};#10; Clk = 0; #10; Clk = 1;
		{RA, RB, RW, BusW, RegWr} = {5'd0, 5'd0, 5'd14, 64'd14, 1'b1};#10; Clk = 0; #10; Clk = 1;
		{RA, RB, RW, BusW, RegWr} = {5'd0, 5'd0, 5'd15, 64'd15, 1'b1};#10; Clk = 0; #10; Clk = 1;
		{RA, RB, RW, BusW, RegWr} = {5'd0, 5'd0, 5'd16, 64'd16, 1'b1};#10; Clk = 0; #10; Clk = 1;
		{RA, RB, RW, BusW, RegWr} = {5'd0, 5'd0, 5'd17, 64'd17, 1'b1};#10; Clk = 0; #10; Clk = 1;
		{RA, RB, RW, BusW, RegWr} = {5'd0, 5'd0, 5'd18, 64'd18, 1'b1};#10; Clk = 0; #10; Clk = 1;
		{RA, RB, RW, BusW, RegWr} = {5'd0, 5'd0, 5'd19, 64'd19, 1'b1};#10; Clk = 0; #10; Clk = 1;
		{RA, RB, RW, BusW, RegWr} = {5'd0, 5'd0, 5'd20, 64'd20, 1'b1};#10; Clk = 0; #10; Clk = 1;
		{RA, RB, RW, BusW, RegWr} = {5'd0, 5'd0, 5'd21, 64'd21, 1'b1};#10; Clk = 0; #10; Clk = 1;
		{RA, RB, RW, BusW, RegWr} = {5'd0, 5'd0, 5'd22, 64'd22, 1'b1};#10; Clk = 0; #10; Clk = 1;
		{RA, RB, RW, BusW, RegWr} = {5'd0, 5'd0, 5'd23, 64'd23, 1'b1};#10; Clk = 0; #10; Clk = 1;
		{RA, RB, RW, BusW, RegWr} = {5'd0, 5'd0, 5'd24, 64'd24, 1'b1};#10; Clk = 0; #10; Clk = 1;
		{RA, RB, RW, BusW, RegWr} = {5'd0, 5'd0, 5'd25, 64'd25, 1'b1};#10; Clk = 0; #10; Clk = 1;
		{RA, RB, RW, BusW, RegWr} = {5'd0, 5'd0, 5'd26, 64'd26, 1'b1};#10; Clk = 0; #10; Clk = 1;
		{RA, RB, RW, BusW, RegWr} = {5'd0, 5'd0, 5'd27, 64'd27, 1'b1};#10; Clk = 0; #10; Clk = 1;
		{RA, RB, RW, BusW, RegWr} = {5'd0, 5'd0, 5'd28, 64'd28, 1'b1};#10; Clk = 0; #10; Clk = 1;
		{RA, RB, RW, BusW, RegWr} = {5'd0, 5'd0, 5'd29, 64'd29, 1'b1};#10; Clk = 0; #10; Clk = 1;
		{RA, RB, RW, BusW, RegWr} = {5'd0, 5'd0, 5'd30, 64'd30, 1'b1};#10; Clk = 0; #10; Clk = 1;
		{RA, RB, RW, BusW, RegWr} = {5'd0, 5'd0, 5'd31, 64'd31, 1'b1};#10; Clk = 0; #10; Clk = 1;

		//Test 1
		{RA, RB, RW, BusW, RegWr} = {5'd0, 5'd1, 5'h0, 64'h0, 1'b0};
		#4;
		passTest(BusA, 64'd0, "BusA reads X0", passed);
		passTest(BusB, 64'd1, "BusA reads X1", passed);
		#6; Clk = 0; #10; Clk = 1;
		passTest(BusA, 64'd0, "BusA reads X0", passed);
		passTest(BusB, 64'd1, "BusA reads X1", passed);

		//Test 2
		{RA, RB, RW, BusW, RegWr} = {5'd2, 5'd3, 5'h1, 64'h1000, 1'b0};
		#4;
		passTest(BusA, 64'd2, "BusA reads X2", passed);
		passTest(BusB, 64'd3, "BusA reads X3", passed);
		#6; Clk = 0; #10; Clk = 1;
		passTest(BusA, 64'd2, "BusA reads X2", passed);
		passTest(BusB, 64'd3, "BusA reads X3", passed);
		
		//Test 3
		{RA, RB, RW, BusW, RegWr} = {5'd4, 5'd5, 5'h0, 64'h1000, 1'b1};
		#4;
		passTest(BusA, 64'd4, "BusA reads X4", passed);
		passTest(BusB, 64'd5, "BusA reads X5", passed);
		#6; Clk = 0; #10; Clk = 1;
		passTest(BusA, 64'd4, "BusA reads X4", passed);
		passTest(BusB, 64'd5, "BusA reads X5", passed);
		
		//Test 4
		{RA, RB, RW, BusW, RegWr} = {5'd6, 5'd7, 5'hA, 64'h1010, 1'b1};
		#4;
		passTest(BusA, 64'd6, "BusA reads X6", passed);
		passTest(BusB, 64'd7, "BusA reads X7", passed);
		#6; Clk = 0; #10; Clk = 1;
		passTest(BusA, 64'd6, "BusA reads X6", passed);
		passTest(BusB, 64'd7, "BusA reads X7", passed);
		
		//Test 5
		{RA, RB, RW, BusW, RegWr} = {5'd8, 5'd9, 5'hB, 64'h103000, 1'b1};
		#4;
		passTest(BusA, 64'd8, "BusA reads X8", passed);
		passTest(BusB, 64'd9, "BusA reads X9", passed);
		#6; Clk = 0; #10; Clk = 1;
		passTest(BusA, 64'd8, "BusA reads X8", passed);
		passTest(BusB, 64'd9, "BusA reads X9", passed);
		
		//Test 6
		{RA, RB, RW, BusW, RegWr} = {5'hA, 5'hB, 5'hC, 64'h0, 1'b0};
		#4;
		passTest(BusA, 64'h1010, "BusA reads X10", passed);
		passTest(BusB, 64'h103000, "BusA reads X11", passed);
		#6; Clk = 0; #10; Clk = 1;
		passTest(BusA, 64'h1010, "BusA reads X10", passed);
		passTest(BusB, 64'h103000, "BusA reads X11", passed);
		
		//Test 7
		{RA, RB, RW, BusW, RegWr} = {5'hC, 5'hD, 5'hD, 64'hABCD, 1'b1};
		#4;
		passTest(BusA, 64'd12, "BusA reads X12", passed);
		passTest(BusB, 64'd13, "BusA reads X13", passed);
		#6; Clk = 0; #10; Clk = 1;
		passTest(BusA, 64'd12, "BusA reads X12", passed);
		passTest(BusB, 64'hABCD, "BusA reads X13", passed);
		
		//Test 8
		{RA, RB, RW, BusW, RegWr} = {5'hE, 5'hF, 5'hE, 64'h9080009, 1'b0};
		#4;
		passTest(BusA, 64'd14, "BusA reads X14", passed);
		passTest(BusB, 64'd15, "BusA reads X15", passed);
		#6; Clk = 0; #10; Clk = 1;
		passTest(BusA, 64'd14, "BusA reads X14", passed);
		passTest(BusB, 64'd15, "BusA reads X15", passed);

		allPassed(passed, 38);
	end
      
endmodule

Lab08/RegisterFileTest2_v.vcd
$date
	Mon Nov  9 14:41:02 2020
$end
$version
	Icarus Verilog
$end
$timescale
	1ps
$end
$scope module RegisterFileTest2_v $end
$var wire 64 ! BusB [63:0] $end
$var wire 64 " BusA [63:0] $end
$var reg 64 # BusW [63:0] $end
$var reg 1 $ Clk $end
$var reg 5 % RA [4:0] $end
$var reg 5 & RB [4:0] $end
$var reg 5 ' RW [4:0] $end
$var reg 1 ( RegWr $end
$var reg 8 ) passed [7:0] $end
$scope module dut $end
$var wire 64 * BusA [63:0] $end
$var wire 64 + BusB [63:0] $end
$var wire 64 , BusW [63:0] $end
$var wire 1 $ Clk $end
$var wire 5 - RA [4:0] $end
$var wire 5 . RB [4:0] $end
$var wire 5 / RW [4:0] $end
$var wire 1 ( RegWr $end
$upscope $end
$scope task allPassed $end
$var reg 8 0 numTests [7:0] $end
$var reg 8 1 passed [7:0] $end
$upscope $end
$scope task passTest $end
$var reg 64 2 actualOut [63:0] $end
$var reg 64 3 expectedOut [63:0] $end
$var reg 8 4 passed [7:0] $end
$var reg 257 5 testType [256:0] $end
$upscope $end
$upscope $end
$enddefinitions $end
#0
$dumpvars
bx 5
bx 4
bx 3
bx 2
bx 1
bx 0
b0 /
b0 .
b0 -
b0 ,
bx +
bx *
b0 )
0(
b0 '
b0 &
b0 %
1$
b0 #
bx "
bx !
$end
#10000
b11111 %
b11111 -
b11111 &
b11111 .
b11111 '
b11111 /
#12000
b0 "
b0 *
b0 !
b0 +
#20000
b10 )
b10 4
b10010010110111001101001011101000110100101100001011011000010000000100100001100000010000001000011011010000110010101100011011010110010000000110010 5
b0 3
b0 2
#30000
0$
#40000
b100 )
b100 4
b10010010110111001101001011101000110100101100001011011000010000000100100001100000010000001000011011010000110010101100011011010110010000000110100 5
b10010001101000101011001111000 #
b10010001101000101011001111000 ,
1(
1$
#50000
0$
#60000
b0 %
b0 -
b0 &
b0 .
b0 '
b0 /
b0 #
b0 ,
b110 )
b110 4
b1001000011000000100000010100110111010001100001011110010111001100100000001100000010000001000011011010000110010101100011011010110010000000110010 5
1$
#62000
bx "
bx *
bx !
bx +
#70000
0$
#75000
b0 "
b0 *
b0 !
b0 +
#80000
b1 '
b1 /
b1 #
b1 ,
1$
#90000
0$
#100000
b10 '
b10 /
b10 #
b10 ,
1$
#110000
0$
#120000
b11 '
b11 /
b11 #
b11 ,
1$
#130000
0$
#140000
b100 '
b100 /
b100 #
b100 ,
1$
#150000
0$
#160000
b101 '
b101 /
b101 #
b101 ,
1$
#170000
0$
#180000
b110 '
b110 /
b110 #
b110 ,
1$
#190000
0$
#200000
b111 '
b111 /
b111 #
b111 ,
1$
#210000
0$
#220000
b1000 '
b1000 /
b1000 #
b1000 ,
1$
#230000
0$
#240000
b1001 '
b1001 /
b1001 #
b1001 ,
1$
#250000
0$
#260000
b1010 '
b1010 /
b1010 #
b1010 ,
1$
#270000
0$
#280000
b1011 '
b1011 /
b1011 #
b1011 ,
1$
#290000
0$
#300000
b1100 '
b1100 /
b1100 #
b1100 ,
1$
#310000
0$
#320000
b1101 '
b1101 /
b1101 #
b1101 ,
1$
#330000
0$
#340000
b1110 '
b1110 /
b1110 #
b1110 ,
1$
#350000
0$
#360000
b1111 '
b1111 /
b1111 #
b1111 ,
1$
#370000
0$
#380000
b10000 '
b10000 /
b10000 #
b10000 ,
1$
#390000
0$
#400000
b10001 '
b10001 /
b10001 #
b10001 ,
1$
#410000
0$
#420000
b10010 '
b10010 /
b10010 #
b10010 ,
1$
#430000
0$
#440000
b10011 '
b10011 /
b10011 #
b10011 ,
1$
#450000
0$
#460000
b10100 '
b10100 /
b10100 #
b10100 ,
1$
#470000
0$
#480000
b10101 '
b10101 /
b10101 #
b10101 ,
1$
#490000
0$
#500000
b10110 '
b10110 /
b10110 #
b10110 ,
1$
#510000
0$
#520000
b10111 '
b10111 /
b10111 #
b10111 ,
1$
#530000
0$
#540000
b11000 '
b11000 /
b11000 #
b11000 ,
1$
#550000
0$
#560000
b11001 '
b11001 /
b11001 #
b11001 ,
1$
#570000
0$
#580000
b11010 '
b11010 /
b11010 #
b11010 ,
1$
#590000
0$
#600000
b11011 '
b11011 /
b11011 #
b11011 ,
1$
#610000
0$
#620000
b11100 '
b11100 /
b11100 #
b11100 ,
1$
#630000
0$
#640000
b11101 '
b11101 /
b11101 #
b11101 ,
1$
#650000
0$
#660000
b11110 '
b11110 /
b11110 #
b11110 ,
1$
#670000
0$
#680000
b11111 '
b11111 /
b11111 #
b11111 ,
1$
#690000
0$
#700000
b1 &
b1 .
b0 '
b0 /
b0 #
b0 ,
0(
1$
#702000
b1 !
b1 +
#704000
b1 3
b1 2
b1000 )
b1000 4
b1000010011101010111001101000001001000000111001001100101011000010110010001110011001000000101100000110001 5
#710000
0$
#720000
b10 %
b10 -
b11 &
b11 .
b1 '
b1 /
b1000000000000 #
b1000000000000 ,
b1010 )
b1010 4
b1000010011101010111001101000001001000000111001001100101011000010110010001110011001000000101100000110001 5
b1 3
b1 2
1$
#722000
b10 "
b10 *
b11 !
b11 +
#724000
b1100 )
b1100 4
b1000010011101010111001101000001001000000111001001100101011000010110010001110011001000000101100000110011 5
b11 3
b11 2
#730000
0$
#740000
b100 %
b100 -
b101 &
b101 .
b0 '
b0 /
1(
b1110 )
b1110 4
b1000010011101010111001101000001001000000111001001100101011000010110010001110011001000000101100000110011 5
b11 3
b11 2
1$
#742000
b100 "
b100 *
b101 !
b101 +
#744000
b10000 )
b10000 4
b1000010011101010111001101000001001000000111001001100101011000010110010001110011001000000101100000110101 5
b101 3
b101 2
#750000
0$
#760000
b110 %
b110 -
b111 &
b111 .
b1010 '
b1010 /
b1000000010000 #
b1000000010000 ,
b10010 )
b10010 4
b1000010011101010111001101000001001000000111001001100101011000010110010001110011001000000101100000110101 5
b101 3
b101 2
1$
#762000
b110 "
b110 *
b111 !
b111 +
#764000
b10100 )
b10100 4
b1000010011101010111001101000001001000000111001001100101011000010110010001110011001000000101100000110111 5
b111 3
b111 2
#770000
0$
#780000
b1000 %
b1000 -
b1001 &
b1001 .
b1011 '
b1011 /
b100000011000000000000 #
b100000011000000000000 ,
b10110 )
b10110 4
b1000010011101010111001101000001001000000111001001100101011000010110010001110011001000000101100000110111 5
b111 3
b111 2
1$
#782000
b1000 "
b1000 *
b1001 !
b1001 +
#784000
b11000 )
b11000 4
b1000010011101010111001101000001001000000111001001100101011000010110010001110011001000000101100000111001 5
b1001 3
b1001 2
#790000
0$
#800000
b1010 %
b1010 -
b1011 &
b1011 .
b1100 '
b1100 /
b0 #
b0 ,
0(
b11010 )
b11010 4
b1000010011101010111001101000001001000000111001001100101011000010110010001110011001000000101100000111001 5
b1001 3
b1001 2
1$
#802000
b1000000010000 "
b1000000010000 *
b100000011000000000000 !
b100000011000000000000 +
#804000
b11100 )
b11100 4
b100001001110101011100110100000100100000011100100110010101100001011001000111001100100000010110000011000100110001 5
b100000011000000000000 3
b100000011000000000000 2
#810000
0$
#820000
b1100 %
b1100 -
b1101 &
b1101 .
b1101 '
b1101 /
b1010101111001101 #
b1010101111001101 ,
1(
b11110 )
b11110 4
b100001001110101011100110100000100100000011100100110010101100001011001000111001100100000010110000011000100110001 5
b100000011000000000000 3
b100000011000000000000 2
1$
#822000
b1100 "
b1100 *
b1101 !
b1101 +
#824000
b100000 )
b100000 4
b100001001110101011100110100000100100000011100100110010101100001011001000111001100100000010110000011000100110011 5
b1101 3
b1101 2
#830000
0$
#835000
b1010101111001101 !
b1010101111001101 +
#840000
b1110 %
b1110 -
b1111 &
b1111 .
b1110 '
b1110 /
b1001000010000000000000001001 #
b1001000010000000000000001001 ,
0(
b100010 )
b100010 4
b100001001110101011100110100000100100000011100100110010101100001011001000111001100100000010110000011000100110011 5
b1010101111001101 3
b1010101111001101 2
1$
#842000
b1110 "
b1110 *
b1111 !
b1111 +
#844000
b100100 )
b100100 4
b100001001110101011100110100000100100000011100100110010101100001011001000111001100100000010110000011000100110101 5
b1111 3
b1111 2
#850000
0$
#860000
b100110 0
b100110 1
b100110 )
b100110 4
b100001001110101011100110100000100100000011100100110010101100001011001000111001100100000010110000011000100110101 5
b1111 3
b1111 2
1$
